scim_sanity/__init__.py
scim_sanity/__main__.py
scim_sanity/cli.py
scim_sanity/schemas.py
scim_sanity/validator.py
scim_sanity-0.2.0.dist-info/licenses/LICENSE
scim_sanity-0.2.0.dist-info/METADATA
scim_sanity-0.2.0.dist-info/WHEEL
scim_sanity-0.2.0.dist-info/entry_points.txt
scim_sanity-0.2.0.dist-info/top_level.txt
scim_sanity-0.2.0.dist-info/RECORD
