Metadata-Version: 2.4
Name: scim-sanity
Version: 0.2.0
Summary: A zero-dependency CLI tool for validating SCIM 2.0 User, Group, Agent, and AgenticApplication payloads (RFC 7643/7644)
Author-email: Thomas Betz <thomas@seattlecodestudio.com>
License: MIT
Project-URL: Homepage, https://github.com/thomaselliottbetz/scim-sanity
Project-URL: Documentation, https://github.com/thomaselliottbetz/scim-sanity#readme
Project-URL: Repository, https://github.com/thomaselliottbetz/scim-sanity
Project-URL: Issues, https://github.com/thomaselliottbetz/scim-sanity/issues
Keywords: scim,scim2,validation,rfc7643,rfc7644,cli,identity,agent,agentic
Classifier: Development Status :: 4 - Beta
Classifier: Intended Audience :: Developers
Classifier: License :: OSI Approved :: MIT License
Classifier: Programming Language :: Python :: 3
Classifier: Programming Language :: Python :: 3.7
Classifier: Programming Language :: Python :: 3.8
Classifier: Programming Language :: Python :: 3.9
Classifier: Programming Language :: Python :: 3.10
Classifier: Programming Language :: Python :: 3.11
Classifier: Programming Language :: Python :: 3.12
Classifier: Topic :: Software Development :: Libraries :: Python Modules
Classifier: Topic :: System :: Systems Administration :: Authentication/Directory
Requires-Python: >=3.7
License-File: LICENSE
Provides-Extra: dev
Requires-Dist: pytest>=7.0.0; extra == "dev"
Requires-Dist: click>=8.0.0; extra == "dev"
Requires-Dist: jsonschema>=4.0.0; extra == "dev"
Dynamic: license-file
